{
  "user": [
    {
      "id": "2fcf",
      "name": "Nguy",
      "mobileNumber": "123",
      "email": "123@gmail.com",
      "Password": "123",
      "status": true
    },
    {
      "id": "33a6",
      "name": "1231",
      "mobileNumber": "123",
      "email": "2131@gmail.com",
      "Password": "123",
      "status": true
    },
    {
      "id": "7291",
      "name": "123",
      "mobileNumber": "123",
      "email": "123",
      "password": "123",
      "status": true
    },
    {
      "id": "a799",
      "name": "Helli",
      "mobileNumber": "13",
      "email": "123@gmail.com",
      "password": "1233",
      "status": true
    },
    {
      "id": "40fe",
      "name": "Nguyễn Hoàn Triều",
      "mobileNumber": "123",
      "email": "123@gmail.com",
      "password": "1234",
      "status": true
    }
  ]
}